{
  "long_reversal": {
    "timestamp": "2025-09-05 13:10:28.910348",
    "scanner": "long_reversal",
    "total_stocks": 17,
    "file_path": "/Users/maverick/PycharmProjects/India-TS/Daily/results/Long_Reversal_Daily_20250905_131028.xlsx",
    "type": "bullish",
    "tickers": [
      "SUNTECK",
      "GMDCLTD",
      "VIJAYA",
      "VARROC",
      "CLEAN",
      "GLENMARK",
      "MSUMI",
      "TRIVENI",
      "SYRMA",
      "SKFINDIA",
      "IMFA",
      "METROBRAND",
      "M&M",
      "KPIL",
      "EICHERMOT",
      "BEML",
      "KFINTECH"
    ]
  },
  "short_reversal": {
    "timestamp": "2025-09-05 13:10:28.916788",
    "scanner": "short_reversal",
    "total_stocks": 37,
    "file_path": "/Users/maverick/PycharmProjects/India-TS/Daily/results-s/Short_Reversal_Daily_20250905_131028.xlsx",
    "type": "bearish",
    "tickers": [
      "QUESS",
      "UBL",
      "360ONE",
      "COROMANDEL",
      "ALLCARGO",
      "JUBLINGREA",
      "MCX",
      "PERSISTENT",
      "PETRONET",
      "PEL",
      "SBICARD",
      "REDINGTON",
      "JBCHEPHARM",
      "SANOFI",
      "SOBHA",
      "TCS",
      "UCOBANK",
      "UJJIVANSFB",
      "JIOFIN",
      "IRB",
      "NAUKRI",
      "BHEL",
      "SIGACHI",
      "SMSPHARMA",
      "SUZLON",
      "VTL",
      "ABBOTINDIA",
      "AXISBANK",
      "BPCL",
      "PANACEABIO",
      "CASTROLIND",
      "CHEMPLASTS",
      "DEEPAKNTR",
      "DIVISLAB",
      "GMMPFAUDLR",
      "FLUOROCHEM",
      "VAIBHAVGBL"
    ]
  }
}