{
  "timestamp": "2025-07-31T10:45:28.379175",
  "user": "Sai",
  "tracker_type": "short_momentum",
  "persistence_days": 3,
  "total_tickers": 124,
  "results": [
    {
      "ticker": "JISLJALEQS",
      "timestamp": "2025-07-31 10:45:17",
      "close": 50.96,
      "volume": 0,
      "vsr": 0.0,
      "price_change_1h": -0.45,
      "price_change_3h": -0.93,
      "price_change_1d": -0.41,
      "rsi": 50.0,
      "bb_position": 0.5,
      "atr": 0.055714285714286306,
      "sector": "Industrials",
      "volume_ratio": 0.0,
      "momentum_score": 20,
      "momentum_status": "Neutral",
      "appearances": 14,
      "persistence_score": 140,
      "total_score": 160
    },
    {
      "ticker": "DABUR",
      "timestamp": "2025-07-31 10:45:17",
      "close": 527.5,
      "volume": 11039,
      "vsr": 0.35135002279238303,
      "price_change_1h": 1.27,
      "price_change_3h": 0.95,
      "price_change_1d": -0.26,
      "rsi": 50.0,
      "bb_position": 0.5,
      "atr": 0.7285714285714319,
      "sector": "Consumer Defensive",
      "volume_ratio": 0.905251590894181,
      "momentum_score": 20,
      "momentum_status": "Neutral",
      "appearances": 10,
      "persistence_score": 100,
      "total_score": 120
    },
    {
      "ticker": "KEC",
      "timestamp": "2025-07-31 10:45:17",
      "close": 871.2,
      "volume": 0,
      "vsr": 0.0,
      "price_change_1h": -1.39,
      "price_change_3h": 0.35,
      "price_change_1d": 1.21,
      "rsi": 50.0,
      "bb_position": 0.5,
      "atr": 0.7142857142857143,
      "sector": "Unknown",
      "volume_ratio": 0.0,
      "momentum_score": 40,
      "momentum_status": "Weak Short",
      "appearances": 12,
      "persistence_score": 120,
      "total_score": 160
    },
    {
      "ticker": "BANKINDIA",
      "timestamp": "2025-07-31 10:45:18",
      "close": 111.41,
      "volume": 12563,
      "vsr": 0.47695701198568,
      "price_change_1h": -0.93,
      "price_change_3h": -3.04,
      "price_change_1d": -1.42,
      "rsi": 50.0,
      "bb_position": 0.5,
      "atr": 0.10785714285714525,
      "sector": "Financial Services",
      "volume_ratio": 0.7929534882253066,
      "momentum_score": 65,
      "momentum_status": "Short",
      "appearances": 1,
      "persistence_score": 10,
      "total_score": 75
    },
    {
      "ticker": "BHEL",
      "timestamp": "2025-07-31 10:45:18",
      "close": 238.65,
      "volume": 2560,
      "vsr": 0.16996217345767606,
      "price_change_1h": -0.73,
      "price_change_3h": -1.2,
      "price_change_1d": -0.58,
      "rsi": 50.0,
      "bb_position": 0.5,
      "atr": 0.3357142857142869,
      "sector": "Industrials",
      "volume_ratio": 0.24714360877939054,
      "momentum_score": 65,
      "momentum_status": "Short",
      "appearances": 3,
      "persistence_score": 30,
      "total_score": 95
    },
    {
      "ticker": "BSE",
      "timestamp": "2025-07-31 10:45:18",
      "close": 2428.1,
      "volume": 458,
      "vsr": 0.09913386901809824,
      "price_change_1h": -0.53,
      "price_change_3h": -1.42,
      "price_change_1d": -0.57,
      "rsi": 50.0,
      "bb_position": 0.5,
      "atr": 1.6928571428572272,
      "sector": "Financial Services",
      "volume_ratio": 0.15930434782608696,
      "momentum_score": 65,
      "momentum_status": "Short",
      "appearances": 12,
      "persistence_score": 120,
      "total_score": 185
    },
    {
      "ticker": "IRCON",
      "timestamp": "2025-07-31 10:45:18",
      "close": 177.39,
      "volume": 2,
      "vsr": 0.0006002991490758064,
      "price_change_1h": -0.5,
      "price_change_3h": -1.44,
      "price_change_1d": -0.55,
      "rsi": 50.0,
      "bb_position": 0.5,
      "atr": 0.14642857142856616,
      "sector": "Industrials",
      "volume_ratio": 0.0010911372377860825,
      "momentum_score": 45,
      "momentum_status": "Weak Short",
      "appearances": 13,
      "persistence_score": 130,
      "total_score": 175
    },
    {
      "ticker": "PIDILITIND",
      "timestamp": "2025-07-31 10:45:18",
      "close": 2854.8,
      "volume": 4,
      "vsr": 0.001368363437327649,
      "price_change_1h": -0.01,
      "price_change_3h": -0.58,
      "price_change_1d": -0.63,
      "rsi": 50.0,
      "bb_position": 0.5,
      "atr": 1.928571428571461,
      "sector": "Unknown",
      "volume_ratio": 0.02789400278940028,
      "momentum_score": 20,
      "momentum_status": "Neutral",
      "appearances": 4,
      "persistence_score": 40,
      "total_score": 60
    },
    {
      "ticker": "GLAXO",
      "timestamp": "2025-07-31 10:45:18",
      "close": 3161.3,
      "volume": 6,
      "vsr": 0.07718282682096668,
      "price_change_1h": 0.14,
      "price_change_3h": -0.9,
      "price_change_1d": -1.15,
      "rsi": 50.0,
      "bb_position": 0.5,
      "atr": 0.8285714285714546,
      "sector": "Healthcare",
      "volume_ratio": 0.31007751937984496,
      "momentum_score": 20,
      "momentum_status": "Neutral",
      "appearances": 1,
      "persistence_score": 10,
      "total_score": 30
    },
    {
      "ticker": "ZFCVINDIA",
      "timestamp": "2025-07-31 10:45:18",
      "close": 13277.0,
      "volume": 0,
      "vsr": 0.0,
      "price_change_1h": -0.05,
      "price_change_3h": -0.77,
      "price_change_1d": -0.7,
      "rsi": 50.0,
      "bb_position": 0.5,
      "atr": 6.714285714285714,
      "sector": "Unknown",
      "volume_ratio": 0.0,
      "momentum_score": 20,
      "momentum_status": "Neutral",
      "appearances": 9,
      "persistence_score": 90,
      "total_score": 110
    },
    {
      "ticker": "ESCORTS",
      "timestamp": "2025-07-31 10:45:18",
      "close": 3378.1,
      "volume": 0,
      "vsr": 0.0,
      "price_change_1h": -0.49,
      "price_change_3h": -1.47,
      "price_change_1d": -1.02,
      "rsi": 50.0,
      "bb_position": 0.5,
      "atr": 1.628571428571409,
      "sector": "Industrials",
      "volume_ratio": 0.0,
      "momentum_score": 45,
      "momentum_status": "Weak Short",
      "appearances": 8,
      "persistence_score": 80,
      "total_score": 125
    },
    {
      "ticker": "AARTIIND",
      "timestamp": "2025-07-31 10:45:18",
      "close": 424.4,
      "volume": 3786,
      "vsr": 0.10769876287841933,
      "price_change_1h": -1.77,
      "price_change_3h": -5.59,
      "price_change_1d": -2.77,
      "rsi": 50.0,
      "bb_position": 0.5,
      "atr": 0.8821428571428466,
      "sector": "Basic Materials",
      "volume_ratio": 0.3283764620168351,
      "momentum_score": 95,
      "momentum_status": "Strong Short",
      "appearances": 1,
      "persistence_score": 10,
      "total_score": 105
    },
    {
      "ticker": "GRINDWELL",
      "timestamp": "2025-07-31 10:45:18",
      "close": 1549.6,
      "volume": 0,
      "vsr": 0.0,
      "price_change_1h": -0.03,
      "price_change_3h": -1.29,
      "price_change_1d": -1.11,
      "rsi": 50.0,
      "bb_position": 0.5,
      "atr": 0.5928571428571233,
      "sector": "Industrials",
      "volume_ratio": 0.0,
      "momentum_score": 45,
      "momentum_status": "Weak Short",
      "appearances": 6,
      "persistence_score": 60,
      "total_score": 105
    },
    {
      "ticker": "PANACEABIO",
      "timestamp": "2025-07-31 10:45:18",
      "close": 403.15,
      "volume": 690,
      "vsr": 0.4430071447812589,
      "price_change_1h": -1.66,
      "price_change_3h": -2.79,
      "price_change_1d": -0.57,
      "rsi": 50.0,
      "bb_position": 0.5,
      "atr": 0.9249999999999952,
      "sector": "Healthcare",
      "volume_ratio": 0.7998145357598238,
      "momentum_score": 65,
      "momentum_status": "Short",
      "appearances": 2,
      "persistence_score": 20,
      "total_score": 85
    },
    {
      "ticker": "EICHERMOT",
      "timestamp": "2025-07-31 10:45:18",
      "close": 5444.5,
      "volume": 153,
      "vsr": 0.23761684284091902,
      "price_change_1h": 0.05,
      "price_change_3h": -1.06,
      "price_change_1d": -0.82,
      "rsi": 50.0,
      "bb_position": 0.5,
      "atr": 3.9285714285714284,
      "sector": "Consumer Cyclical",
      "volume_ratio": 0.2999117906498089,
      "momentum_score": 45,
      "momentum_status": "Weak Short",
      "appearances": 1,
      "persistence_score": 10,
      "total_score": 55
    },
    {
      "ticker": "CROMPTON",
      "timestamp": "2025-07-31 10:45:19",
      "close": 323.4,
      "volume": 75,
      "vsr": 0.004008851544210547,
      "price_change_1h": 0.15,
      "price_change_3h": -0.42,
      "price_change_1d": -0.26,
      "rsi": 50.0,
      "bb_position": 0.5,
      "atr": 0.2571428571428588,
      "sector": "Consumer Cyclical",
      "volume_ratio": 0.022893423482547578,
      "momentum_score": 20,
      "momentum_status": "Neutral",
      "appearances": 8,
      "persistence_score": 80,
      "total_score": 100
    },
    {
      "ticker": "PNB",
      "timestamp": "2025-07-31 10:45:19",
      "close": 104.03,
      "volume": 16178,
      "vsr": 0.10509924271114426,
      "price_change_1h": -2.14,
      "price_change_3h": -4.0,
      "price_change_1d": -1.58,
      "rsi": 50.0,
      "bb_position": 0.5,
      "atr": 0.09428571428571685,
      "sector": "Unknown",
      "volume_ratio": 0.20804572942352764,
      "momentum_score": 65,
      "momentum_status": "Short",
      "appearances": 3,
      "persistence_score": 30,
      "total_score": 95
    },
    {
      "ticker": "INFY",
      "timestamp": "2025-07-31 10:45:19",
      "close": 1502.6,
      "volume": 464,
      "vsr": 0.005958830772096859,
      "price_change_1h": 0.11,
      "price_change_3h": -0.89,
      "price_change_1d": -1.18,
      "rsi": 50.0,
      "bb_position": 0.5,
      "atr": 0.8999999999999935,
      "sector": "Technology",
      "volume_ratio": 0.027637801841725936,
      "momentum_score": 20,
      "momentum_status": "Neutral",
      "appearances": 2,
      "persistence_score": 20,
      "total_score": 40
    },
    {
      "ticker": "LT",
      "timestamp": "2025-07-31 10:45:19",
      "close": 3641.6,
      "volume": 925,
      "vsr": 0.228875199730523,
      "price_change_1h": -0.29,
      "price_change_3h": -0.74,
      "price_change_1d": -0.38,
      "rsi": 50.0,
      "bb_position": 0.5,
      "atr": 1.5928571428571558,
      "sector": "Unknown",
      "volume_ratio": 0.3875968992248062,
      "momentum_score": 20,
      "momentum_status": "Neutral",
      "appearances": 5,
      "persistence_score": 50,
      "total_score": 70
    },
    {
      "ticker": "SHREECEM",
      "timestamp": "2025-07-31 10:45:19",
      "close": 30715.0,
      "volume": 0,
      "vsr": 0.0,
      "price_change_1h": 0.26,
      "price_change_3h": 0.21,
      "price_change_1d": 0.33,
      "rsi": 50.0,
      "bb_position": 0.5,
      "atr": 7.857142857142857,
      "sector": "Unknown",
      "volume_ratio": 0.0,
      "momentum_score": 20,
      "momentum_status": "Neutral",
      "appearances": 1,
      "persistence_score": 10,
      "total_score": 30
    },
    {
      "ticker": "INDIACEM",
      "timestamp": "2025-07-31 10:45:19",
      "close": 370.15,
      "volume": 0,
      "vsr": 0.0,
      "price_change_1h": -1.39,
      "price_change_3h": 0.61,
      "price_change_1d": 1.21,
      "rsi": 50.0,
      "bb_position": 0.5,
      "atr": 0.2107142857142971,
      "sector": "Basic Materials",
      "volume_ratio": 0.0,
      "momentum_score": 40,
      "momentum_status": "Weak Short",
      "appearances": 1,
      "persistence_score": 10,
      "total_score": 50
    },
    {
      "ticker": "AVG",
      "timestamp": "2025-07-31 10:45:19",
      "close": 248.2,
      "volume": 0,
      "vsr": 0.0,
      "price_change_1h": 0.49,
      "price_change_3h": 0.08,
      "price_change_1d": 0.77,
      "rsi": 50.0,
      "bb_position": 0.5,
      "atr": 0.16071428571428367,
      "sector": "Unknown",
      "volume_ratio": 0.0,
      "momentum_score": 20,
      "momentum_status": "Neutral",
      "appearances": 1,
      "persistence_score": 10,
      "total_score": 30
    },
    {
      "ticker": "TRIVENI",
      "timestamp": "2025-07-31 10:45:19",
      "close": 341.8,
      "volume": 3308,
      "vsr": 3.583544726603202,
      "price_change_1h": 0.44,
      "price_change_3h": -0.2,
      "price_change_1d": -0.96,
      "rsi": 50.0,
      "bb_position": 0.5,
      "atr": 0.27142857142856414,
      "sector": "Unknown",
      "volume_ratio": 5.719719892798478,
      "momentum_score": 10,
      "momentum_status": "No Signal",
      "appearances": 13,
      "persistence_score": 130,
      "total_score": 140
    },
    {
      "ticker": "QUESS",
      "timestamp": "2025-07-31 10:45:19",
      "close": 295.4,
      "volume": 5,
      "vsr": 0.005114932534039993,
      "price_change_1h": -0.69,
      "price_change_3h": -1.19,
      "price_change_1d": -0.13,
      "rsi": 50.0,
      "bb_position": 0.5,
      "atr": 0.20000000000000082,
      "sector": "Unknown",
      "volume_ratio": 0.012987012987012988,
      "momentum_score": 65,
      "momentum_status": "Short",
      "appearances": 13,
      "persistence_score": 130,
      "total_score": 195
    },
    {
      "ticker": "ATGL",
      "timestamp": "2025-07-31 10:45:19",
      "close": 616.25,
      "volume": 0,
      "vsr": 0.0,
      "price_change_1h": -0.36,
      "price_change_3h": -2.05,
      "price_change_1d": -1.05,
      "rsi": 50.0,
      "bb_position": 0.5,
      "atr": 0.5428571428571526,
      "sector": "Utilities",
      "volume_ratio": 0.0,
      "momentum_score": 45,
      "momentum_status": "Weak Short",
      "appearances": 8,
      "persistence_score": 80,
      "total_score": 125
    },
    {
      "ticker": "NBCC",
      "timestamp": "2025-07-31 10:45:19",
      "close": 107.47,
      "volume": 1030,
      "vsr": 0.07267787999329821,
      "price_change_1h": -0.85,
      "price_change_3h": -0.99,
      "price_change_1d": -0.29,
      "rsi": 50.0,
      "bb_position": 0.5,
      "atr": 0.10714285714285816,
      "sector": "Industrials",
      "volume_ratio": 0.15600387737792318,
      "momentum_score": 40,
      "momentum_status": "Weak Short",
      "appearances": 12,
      "persistence_score": 120,
      "total_score": 160
    },
    {
      "ticker": "DBL",
      "timestamp": "2025-07-31 10:45:19",
      "close": 481.15,
      "volume": 0,
      "vsr": 0.0,
      "price_change_1h": 0.24,
      "price_change_3h": -0.25,
      "price_change_1d": -0.21,
      "rsi": 50.0,
      "bb_position": 0.5,
      "atr": 0.40357142857142286,
      "sector": "Industrials",
      "volume_ratio": 0.0,
      "momentum_score": 20,
      "momentum_status": "Neutral",
      "appearances": 12,
      "persistence_score": 120,
      "total_score": 140
    },
    {
      "ticker": "BHARATFORG",
      "timestamp": "2025-07-31 10:45:20",
      "close": 1161.3,
      "volume": 294,
      "vsr": 0.05901949349631171,
      "price_change_1h": 0.42,
      "price_change_3h": -1.6,
      "price_change_1d": -2.67,
      "rsi": 50.0,
      "bb_position": 0.5,
      "atr": 1.6928571428571948,
      "sector": "Consumer Cyclical",
      "volume_ratio": 0.10213652944241793,
      "momentum_score": 75,
      "momentum_status": "Short",
      "appearances": 14,
      "persistence_score": 140,
      "total_score": 215
    },
    {
      "ticker": "OPTIEMUS",
      "timestamp": "2025-07-31 10:45:20",
      "close": 578.95,
      "volume": 0,
      "vsr": 0.0,
      "price_change_1h": 0.3,
      "price_change_3h": -1.35,
      "price_change_1d": -1.25,
      "rsi": 50.0,
      "bb_position": 0.5,
      "atr": 0.4249999999999951,
      "sector": "Technology",
      "volume_ratio": 0.0,
      "momentum_score": 45,
      "momentum_status": "Weak Short",
      "appearances": 1,
      "persistence_score": 10,
      "total_score": 55
    },
    {
      "ticker": "LICI",
      "timestamp": "2025-07-31 10:45:20",
      "close": 889.9,
      "volume": 140,
      "vsr": 0.1769376249734651,
      "price_change_1h": -0.35,
      "price_change_3h": -1.54,
      "price_change_1d": -1.4,
      "rsi": 50.0,
      "bb_position": 0.5,
      "atr": 0.703571428571414,
      "sector": "Financial Services",
      "volume_ratio": 0.19844082211197733,
      "momentum_score": 45,
      "momentum_status": "Weak Short",
      "appearances": 1,
      "persistence_score": 10,
      "total_score": 55
    },
    {
      "ticker": "TIINDIA",
      "timestamp": "2025-07-31 10:45:20",
      "close": 2812.1,
      "volume": 39,
      "vsr": 0.06113906786436607,
      "price_change_1h": -0.79,
      "price_change_3h": -1.13,
      "price_change_1d": -0.71,
      "rsi": 50.0,
      "bb_position": 0.5,
      "atr": 2.592857142857156,
      "sector": "Unknown",
      "volume_ratio": 0.1552547770700637,
      "momentum_score": 65,
      "momentum_status": "Short",
      "appearances": 3,
      "persistence_score": 30,
      "total_score": 95
    },
    {
      "ticker": "JINDALSAW",
      "timestamp": "2025-07-31 10:45:20",
      "close": 210.7,
      "volume": 78,
      "vsr": 0.0,
      "price_change_1h": -0.51,
      "price_change_3h": -1.54,
      "price_change_1d": -0.68,
      "rsi": 50.0,
      "bb_position": 0.5,
      "atr": 0.06928571428571015,
      "sector": "Basic Materials",
      "volume_ratio": 0.12125923047026817,
      "momentum_score": 65,
      "momentum_status": "Short",
      "appearances": 4,
      "persistence_score": 40,
      "total_score": 105
    },
    {
      "ticker": "IRB",
      "timestamp": "2025-07-31 10:45:20",
      "close": 45.15,
      "volume": 0,
      "vsr": 0.0,
      "price_change_1h": -0.55,
      "price_change_3h": -1.85,
      "price_change_1d": -1.35,
      "rsi": 50.0,
      "bb_position": 0.5,
      "atr": 0.044285714285713595,
      "sector": "Industrials",
      "volume_ratio": 0.0,
      "momentum_score": 65,
      "momentum_status": "Short",
      "appearances": 12,
      "persistence_score": 120,
      "total_score": 185
    },
    {
      "ticker": "RECLTD",
      "timestamp": "2025-07-31 10:45:20",
      "close": 397.85,
      "volume": 3517,
      "vsr": 0.015187092827923727,
      "price_change_1h": 0.67,
      "price_change_3h": -0.29,
      "price_change_1d": -1.51,
      "rsi": 50.0,
      "bb_position": 0.5,
      "atr": 0.5535714285714245,
      "sector": "Unknown",
      "volume_ratio": 0.1022856494717035,
      "momentum_score": 20,
      "momentum_status": "Neutral",
      "appearances": 1,
      "persistence_score": 10,
      "total_score": 30
    },
    {
      "ticker": "PATELENG",
      "timestamp": "2025-07-31 10:45:20",
      "close": 37.64,
      "volume": 125,
      "vsr": 0.0,
      "price_change_1h": -0.21,
      "price_change_3h": -1.41,
      "price_change_1d": -0.95,
      "rsi": 50.0,
      "bb_position": 0.5,
      "atr": 0.018571428571427923,
      "sector": "Industrials",
      "volume_ratio": 0.060325273876743406,
      "momentum_score": 45,
      "momentum_status": "Weak Short",
      "appearances": 14,
      "persistence_score": 140,
      "total_score": 185
    },
    {
      "ticker": "SIGACHI",
      "timestamp": "2025-07-31 10:45:20",
      "close": 37.67,
      "volume": 11,
      "vsr": 0.0024501205570679513,
      "price_change_1h": -0.97,
      "price_change_3h": -1.39,
      "price_change_1d": -0.34,
      "rsi": 50.0,
      "bb_position": 0.5,
      "atr": 0.027142857142853267,
      "sector": "Healthcare",
      "volume_ratio": 0.004628558204119416,
      "momentum_score": 65,
      "momentum_status": "Short",
      "appearances": 1,
      "persistence_score": 10,
      "total_score": 75
    },
    {
      "ticker": "DMART",
      "timestamp": "2025-07-31 10:45:20",
      "close": 4324.6,
      "volume": 371,
      "vsr": 0.020572610939205375,
      "price_change_1h": -0.14,
      "price_change_3h": 0.67,
      "price_change_1d": 1.04,
      "rsi": 50.0,
      "bb_position": 0.5,
      "atr": 5.4857142857141685,
      "sector": "Consumer Defensive",
      "volume_ratio": 0.09872929279489057,
      "momentum_score": 20,
      "momentum_status": "Neutral",
      "appearances": 6,
      "persistence_score": 60,
      "total_score": 80
    },
    {
      "ticker": "FSL",
      "timestamp": "2025-07-31 10:45:20",
      "close": 331.15,
      "volume": 1070,
      "vsr": 0.08733553168562848,
      "price_change_1h": 0.2,
      "price_change_3h": 0.29,
      "price_change_1d": -1.02,
      "rsi": 50.0,
      "bb_position": 0.5,
      "atr": 0.3178571428571339,
      "sector": "Technology",
      "volume_ratio": 0.36772918635621615,
      "momentum_score": 20,
      "momentum_status": "Neutral",
      "appearances": 2,
      "persistence_score": 20,
      "total_score": 40
    },
    {
      "ticker": "INDHOTEL",
      "timestamp": "2025-07-31 10:45:21",
      "close": 738.0,
      "volume": 682,
      "vsr": 0.1525543154752845,
      "price_change_1h": -0.64,
      "price_change_3h": -1.11,
      "price_change_1d": -0.26,
      "rsi": 50.0,
      "bb_position": 0.5,
      "atr": 0.5892857142857224,
      "sector": "Consumer Cyclical",
      "volume_ratio": 0.2530659195903449,
      "momentum_score": 65,
      "momentum_status": "Short",
      "appearances": 9,
      "persistence_score": 90,
      "total_score": 155
    },
    {
      "ticker": "KPITTECH",
      "timestamp": "2025-07-31 10:45:21",
      "close": 1239.5,
      "volume": 142,
      "vsr": 0.03607173703196459,
      "price_change_1h": -0.19,
      "price_change_3h": 2.09,
      "price_change_1d": -2.07,
      "rsi": 50.0,
      "bb_position": 0.5,
      "atr": 1.2785714285714513,
      "sector": "Technology",
      "volume_ratio": 0.09240580464632003,
      "momentum_score": 50,
      "momentum_status": "Weak Short",
      "appearances": 4,
      "persistence_score": 40,
      "total_score": 90
    },
    {
      "ticker": "HCLTECH",
      "timestamp": "2025-07-31 10:45:21",
      "close": 1467.9,
      "volume": 2616,
      "vsr": 0.0938351793683124,
      "price_change_1h": 0.36,
      "price_change_3h": -0.36,
      "price_change_1d": -0.87,
      "rsi": 50.0,
      "bb_position": 0.5,
      "atr": 1.1571428571428442,
      "sector": "Technology",
      "volume_ratio": 0.2669496714151598,
      "momentum_score": 20,
      "momentum_status": "Neutral",
      "appearances": 6,
      "persistence_score": 60,
      "total_score": 80
    },
    {
      "ticker": "BAYERCROP",
      "timestamp": "2025-07-31 10:45:21",
      "close": 6409.0,
      "volume": 21,
      "vsr": 0.0,
      "price_change_1h": 0.51,
      "price_change_3h": 1.94,
      "price_change_1d": 0.57,
      "rsi": 50.0,
      "bb_position": 0.5,
      "atr": 7.178571428571429,
      "sector": "Basic Materials",
      "volume_ratio": 0.20038167938931298,
      "momentum_score": 20,
      "momentum_status": "Neutral",
      "appearances": 1,
      "persistence_score": 10,
      "total_score": 30
    },
    {
      "ticker": "FIVESTAR",
      "timestamp": "2025-07-31 10:45:21",
      "close": 611.3,
      "volume": 172,
      "vsr": 0.0361417618583669,
      "price_change_1h": 0.71,
      "price_change_3h": -1.4,
      "price_change_1d": -0.52,
      "rsi": 50.0,
      "bb_position": 0.5,
      "atr": 0.6821428571428457,
      "sector": "Financial Services",
      "volume_ratio": 0.12509090909090909,
      "momentum_score": 45,
      "momentum_status": "Weak Short",
      "appearances": 6,
      "persistence_score": 60,
      "total_score": 105
    },
    {
      "ticker": "ABFRL",
      "timestamp": "2025-07-31 10:45:21",
      "close": 73.45,
      "volume": 509,
      "vsr": 0.005136562943081564,
      "price_change_1h": -1.0,
      "price_change_3h": -1.54,
      "price_change_1d": -1.33,
      "rsi": 50.0,
      "bb_position": 0.5,
      "atr": 0.06071428571428531,
      "sector": "Consumer Cyclical",
      "volume_ratio": 0.04843905386822484,
      "momentum_score": 65,
      "momentum_status": "Short",
      "appearances": 2,
      "persistence_score": 20,
      "total_score": 85
    },
    {
      "ticker": "HAL",
      "timestamp": "2025-07-31 10:45:21",
      "close": 4515.0,
      "volume": 101,
      "vsr": 0.01123238128707514,
      "price_change_1h": -0.23,
      "price_change_3h": -0.72,
      "price_change_1d": -0.3,
      "rsi": 50.0,
      "bb_position": 0.5,
      "atr": 5.264285714285701,
      "sector": "Industrials",
      "volume_ratio": 0.07174569348250755,
      "momentum_score": 20,
      "momentum_status": "Neutral",
      "appearances": 3,
      "persistence_score": 30,
      "total_score": 50
    },
    {
      "ticker": "TORNTPOWER",
      "timestamp": "2025-07-31 10:45:21",
      "close": 1320.6,
      "volume": 59,
      "vsr": 0.08970740561243508,
      "price_change_1h": -0.15,
      "price_change_3h": -1.73,
      "price_change_1d": -0.97,
      "rsi": 50.0,
      "bb_position": 0.5,
      "atr": 1.2857142857142858,
      "sector": "Unknown",
      "volume_ratio": 0.18431740081224615,
      "momentum_score": 45,
      "momentum_status": "Weak Short",
      "appearances": 11,
      "persistence_score": 110,
      "total_score": 155
    },
    {
      "ticker": "CHALET",
      "timestamp": "2025-07-31 10:45:21",
      "close": 902.0,
      "volume": 3,
      "vsr": 0.0,
      "price_change_1h": -0.28,
      "price_change_3h": 0.32,
      "price_change_1d": 1.18,
      "rsi": 50.0,
      "bb_position": 0.5,
      "atr": 0.5642857142857126,
      "sector": "Consumer Cyclical",
      "volume_ratio": 0.11090573012939002,
      "momentum_score": 20,
      "momentum_status": "Neutral",
      "appearances": 1,
      "persistence_score": 10,
      "total_score": 30
    },
    {
      "ticker": "MUNJALAU",
      "timestamp": "2025-07-31 10:45:21",
      "close": 76.3,
      "volume": 0,
      "vsr": 0.0,
      "price_change_1h": -0.38,
      "price_change_3h": -1.74,
      "price_change_1d": -1.36,
      "rsi": 50.0,
      "bb_position": 0.5,
      "atr": 0.05214285714285743,
      "sector": "Consumer Cyclical",
      "volume_ratio": 0.0,
      "momentum_score": 45,
      "momentum_status": "Weak Short",
      "appearances": 14,
      "persistence_score": 140,
      "total_score": 185
    },
    {
      "ticker": "POWERGRID",
      "timestamp": "2025-07-31 10:45:21",
      "close": 292.45,
      "volume": 17132,
      "vsr": 0.6574373808248631,
      "price_change_1h": -0.05,
      "price_change_3h": -1.05,
      "price_change_1d": 1.16,
      "rsi": 50.0,
      "bb_position": 0.5,
      "atr": 0.414285714285707,
      "sector": "Unknown",
      "volume_ratio": 0.7305679043933434,
      "momentum_score": 35,
      "momentum_status": "Neutral",
      "appearances": 1,
      "persistence_score": 10,
      "total_score": 45
    },
    {
      "ticker": "HFCL",
      "timestamp": "2025-07-31 10:45:21",
      "close": 75.63,
      "volume": 0,
      "vsr": 0.0,
      "price_change_1h": -0.92,
      "price_change_3h": -2.21,
      "price_change_1d": -1.73,
      "rsi": 50.0,
      "bb_position": 0.5,
      "atr": 0.0721428571428565,
      "sector": "Technology",
      "volume_ratio": 0.0,
      "momentum_score": 65,
      "momentum_status": "Short",
      "appearances": 1,
      "persistence_score": 10,
      "total_score": 75
    },
    {
      "ticker": "ABB",
      "timestamp": "2025-07-31 10:45:22",
      "close": 5501.5,
      "volume": 1059,
      "vsr": 6.174567080636698,
      "price_change_1h": -0.42,
      "price_change_3h": -0.64,
      "price_change_1d": -0.58,
      "rsi": 50.0,
      "bb_position": 0.5,
      "atr": 3.107142857142857,
      "sector": "Industrials",
      "volume_ratio": 4.631532910561994,
      "momentum_score": 10,
      "momentum_status": "No Signal",
      "appearances": 8,
      "persistence_score": 80,
      "total_score": 90
    },
    {
      "ticker": "OIL",
      "timestamp": "2025-07-31 10:45:22",
      "close": 443.15,
      "volume": 1321,
      "vsr": 0.08577430082472406,
      "price_change_1h": 0.54,
      "price_change_3h": -1.34,
      "price_change_1d": -0.83,
      "rsi": 50.0,
      "bb_position": 0.5,
      "atr": 0.3892857142857094,
      "sector": "Unknown",
      "volume_ratio": 0.43755485997250787,
      "momentum_score": 45,
      "momentum_status": "Weak Short",
      "appearances": 2,
      "persistence_score": 20,
      "total_score": 65
    },
    {
      "ticker": "NCC",
      "timestamp": "2025-07-31 10:45:22",
      "close": 218.65,
      "volume": 8176,
      "vsr": 0.33135445591904417,
      "price_change_1h": -0.93,
      "price_change_3h": -1.46,
      "price_change_1d": -0.84,
      "rsi": 50.0,
      "bb_position": 0.5,
      "atr": 0.22428571428571129,
      "sector": "Industrials",
      "volume_ratio": 2.505554448922054,
      "momentum_score": 75,
      "momentum_status": "Short",
      "appearances": 1,
      "persistence_score": 10,
      "total_score": 85
    },
    {
      "ticker": "FINCABLES",
      "timestamp": "2025-07-31 10:45:22",
      "close": 884.65,
      "volume": 401,
      "vsr": 0.37145106757444696,
      "price_change_1h": -1.1,
      "price_change_3h": -0.81,
      "price_change_1d": -0.06,
      "rsi": 50.0,
      "bb_position": 0.5,
      "atr": 0.7071428571428717,
      "sector": "Industrials",
      "volume_ratio": 0.8959892749413473,
      "momentum_score": 40,
      "momentum_status": "Weak Short",
      "appearances": 12,
      "persistence_score": 120,
      "total_score": 160
    },
    {
      "ticker": "ICICIPRULI",
      "timestamp": "2025-07-31 10:45:22",
      "close": 611.0,
      "volume": 243,
      "vsr": 0.046059692793230515,
      "price_change_1h": -0.82,
      "price_change_3h": -1.63,
      "price_change_1d": -1.2,
      "rsi": 50.0,
      "bb_position": 0.5,
      "atr": 0.525000000000026,
      "sector": "Financial Services",
      "volume_ratio": 0.14396161023727005,
      "momentum_score": 65,
      "momentum_status": "Short",
      "appearances": 1,
      "persistence_score": 10,
      "total_score": 75
    },
    {
      "ticker": "APOLLO",
      "timestamp": "2025-07-31 10:45:22",
      "close": 173.91,
      "volume": 1865,
      "vsr": 0.12712461317309673,
      "price_change_1h": -0.56,
      "price_change_3h": 1.67,
      "price_change_1d": 1.94,
      "rsi": 50.0,
      "bb_position": 0.5,
      "atr": 0.25000000000000205,
      "sector": "Unknown",
      "volume_ratio": 0.39908413934777026,
      "momentum_score": 40,
      "momentum_status": "Weak Short",
      "appearances": 14,
      "persistence_score": 140,
      "total_score": 180
    },
    {
      "ticker": "COFORGE",
      "timestamp": "2025-07-31 10:45:22",
      "close": 1708.6,
      "volume": 2086,
      "vsr": 0.7540308661052902,
      "price_change_1h": -0.86,
      "price_change_3h": -1.86,
      "price_change_1d": -1.47,
      "rsi": 50.0,
      "bb_position": 0.5,
      "atr": 1.3285714285714383,
      "sector": "Technology",
      "volume_ratio": 0.6981959366736955,
      "momentum_score": 55,
      "momentum_status": "Weak Short",
      "appearances": 2,
      "persistence_score": 20,
      "total_score": 75
    },
    {
      "ticker": "TEJASNET",
      "timestamp": "2025-07-31 10:45:22",
      "close": 582.1,
      "volume": 247,
      "vsr": 0.15091649694502374,
      "price_change_1h": -0.5,
      "price_change_3h": -1.45,
      "price_change_1d": -0.59,
      "rsi": 50.0,
      "bb_position": 0.5,
      "atr": 0.6071428571428653,
      "sector": "Unknown",
      "volume_ratio": 0.30973728760423846,
      "momentum_score": 45,
      "momentum_status": "Weak Short",
      "appearances": 1,
      "persistence_score": 10,
      "total_score": 55
    },
    {
      "ticker": "CONCOR",
      "timestamp": "2025-07-31 10:45:22",
      "close": 578.4,
      "volume": 62,
      "vsr": 0.010687830870248124,
      "price_change_1h": -0.87,
      "price_change_3h": -2.64,
      "price_change_1d": -0.26,
      "rsi": 50.0,
      "bb_position": 0.5,
      "atr": 0.37857142857143344,
      "sector": "Industrials",
      "volume_ratio": 0.02378759975445058,
      "momentum_score": 65,
      "momentum_status": "Short",
      "appearances": 4,
      "persistence_score": 40,
      "total_score": 105
    },
    {
      "ticker": "CENTRALBK",
      "timestamp": "2025-07-31 10:45:22",
      "close": 36.09,
      "volume": 755,
      "vsr": 0.10274182317973944,
      "price_change_1h": -0.5,
      "price_change_3h": -1.85,
      "price_change_1d": -1.17,
      "rsi": 50.0,
      "bb_position": 0.5,
      "atr": 0.023571428571429465,
      "sector": "Financial Services",
      "volume_ratio": 0.11680797079027166,
      "momentum_score": 45,
      "momentum_status": "Weak Short",
      "appearances": 12,
      "persistence_score": 120,
      "total_score": 165
    },
    {
      "ticker": "CSBBANK",
      "timestamp": "2025-07-31 10:45:22",
      "close": 419.5,
      "volume": 361,
      "vsr": 0.0,
      "price_change_1h": -1.99,
      "price_change_3h": -0.13,
      "price_change_1d": 1.65,
      "rsi": 50.0,
      "bb_position": 0.5,
      "atr": 0.5464285714285698,
      "sector": "Financial Services",
      "volume_ratio": 0.6249459014974466,
      "momentum_score": 40,
      "momentum_status": "Weak Short",
      "appearances": 1,
      "persistence_score": 10,
      "total_score": 50
    },
    {
      "ticker": "APLAPOLLO",
      "timestamp": "2025-07-31 10:45:22",
      "close": 1565.0,
      "volume": 0,
      "vsr": 0.0,
      "price_change_1h": -0.1,
      "price_change_3h": -0.06,
      "price_change_1d": 0.05,
      "rsi": 50.0,
      "bb_position": 0.5,
      "atr": 0.6999999999999805,
      "sector": "Basic Materials",
      "volume_ratio": 0.0,
      "momentum_score": 20,
      "momentum_status": "Neutral",
      "appearances": 1,
      "persistence_score": 10,
      "total_score": 30
    },
    {
      "ticker": "GICRE",
      "timestamp": "2025-07-31 10:45:23",
      "close": 383.85,
      "volume": 0,
      "vsr": 0.0,
      "price_change_1h": -1.22,
      "price_change_3h": -0.3,
      "price_change_1d": 1.74,
      "rsi": 50.0,
      "bb_position": 0.5,
      "atr": 0.5357142857142898,
      "sector": "Financial Services",
      "volume_ratio": 0.0,
      "momentum_score": 40,
      "momentum_status": "Weak Short",
      "appearances": 1,
      "persistence_score": 10,
      "total_score": 50
    },
    {
      "ticker": "WELCORP",
      "timestamp": "2025-07-31 10:45:23",
      "close": 927.95,
      "volume": 277,
      "vsr": 0.703549496103999,
      "price_change_1h": 0.41,
      "price_change_3h": -1.13,
      "price_change_1d": -1.66,
      "rsi": 50.0,
      "bb_position": 0.5,
      "atr": 0.8142857142857289,
      "sector": "Unknown",
      "volume_ratio": 0.8987670343932511,
      "momentum_score": 35,
      "momentum_status": "Neutral",
      "appearances": 2,
      "persistence_score": 20,
      "total_score": 55
    },
    {
      "ticker": "PEL",
      "timestamp": "2025-07-31 10:45:23",
      "close": 1242.0,
      "volume": 160,
      "vsr": 0.0,
      "price_change_1h": -2.22,
      "price_change_3h": -4.28,
      "price_change_1d": -1.31,
      "rsi": 50.0,
      "bb_position": 0.5,
      "atr": 1.8785714285714417,
      "sector": "Unknown",
      "volume_ratio": 0.048157233366943074,
      "momentum_score": 65,
      "momentum_status": "Short",
      "appearances": 7,
      "persistence_score": 70,
      "total_score": 135
    },
    {
      "ticker": "PHOENIXLTD",
      "timestamp": "2025-07-31 10:45:23",
      "close": 1475.5,
      "volume": 8,
      "vsr": 0.0011719422378972321,
      "price_change_1h": -1.1,
      "price_change_3h": -1.48,
      "price_change_1d": -1.5,
      "rsi": 50.0,
      "bb_position": 0.5,
      "atr": 1.1571428571428604,
      "sector": "Unknown",
      "volume_ratio": 0.011004126547455296,
      "momentum_score": 65,
      "momentum_status": "Short",
      "appearances": 2,
      "persistence_score": 20,
      "total_score": 85
    },
    {
      "ticker": "JUBLFOOD",
      "timestamp": "2025-07-31 10:45:23",
      "close": 657.15,
      "volume": 1,
      "vsr": 0.00014961492857760284,
      "price_change_1h": -0.13,
      "price_change_3h": -0.24,
      "price_change_1d": 0.33,
      "rsi": 50.0,
      "bb_position": 0.5,
      "atr": 0.5678571428571705,
      "sector": "Consumer Cyclical",
      "volume_ratio": 0.0010981167298083786,
      "momentum_score": 20,
      "momentum_status": "Neutral",
      "appearances": 3,
      "persistence_score": 30,
      "total_score": 50
    },
    {
      "ticker": "KANSAINER",
      "timestamp": "2025-07-31 10:45:23",
      "close": 242.0,
      "volume": 155,
      "vsr": 0.2145551441325961,
      "price_change_1h": -0.35,
      "price_change_3h": -1.49,
      "price_change_1d": -1.14,
      "rsi": 50.0,
      "bb_position": 0.5,
      "atr": 0.18571428571428328,
      "sector": "Basic Materials",
      "volume_ratio": 0.8043591074208615,
      "momentum_score": 45,
      "momentum_status": "Weak Short",
      "appearances": 1,
      "persistence_score": 10,
      "total_score": 55
    },
    {
      "ticker": "RCF",
      "timestamp": "2025-07-31 10:45:23",
      "close": 152.78,
      "volume": 42,
      "vsr": 0.0,
      "price_change_1h": -0.96,
      "price_change_3h": -1.13,
      "price_change_1d": -1.57,
      "rsi": 50.0,
      "bb_position": 0.5,
      "atr": 0.10714285714285511,
      "sector": "Unknown",
      "volume_ratio": 0.020724365933089905,
      "momentum_score": 65,
      "momentum_status": "Short",
      "appearances": 1,
      "persistence_score": 10,
      "total_score": 75
    },
    {
      "ticker": "DEEPAKFERT",
      "timestamp": "2025-07-31 10:45:23",
      "close": 1572.5,
      "volume": 402,
      "vsr": 0.23814813169238475,
      "price_change_1h": -0.44,
      "price_change_3h": -0.12,
      "price_change_1d": 0.7,
      "rsi": 50.0,
      "bb_position": 0.5,
      "atr": 3.1857142857142953,
      "sector": "Basic Materials",
      "volume_ratio": 0.42848006821573226,
      "momentum_score": 20,
      "momentum_status": "Neutral",
      "appearances": 9,
      "persistence_score": 90,
      "total_score": 110
    },
    {
      "ticker": "COLPAL",
      "timestamp": "2025-07-31 10:45:23",
      "close": 2232.9,
      "volume": 4,
      "vsr": 0.0,
      "price_change_1h": 0.41,
      "price_change_3h": -0.25,
      "price_change_1d": -0.56,
      "rsi": 50.0,
      "bb_position": 0.5,
      "atr": 2.157142857142909,
      "sector": "Consumer Defensive",
      "volume_ratio": 0.0015449383955814763,
      "momentum_score": 20,
      "momentum_status": "Neutral",
      "appearances": 2,
      "persistence_score": 20,
      "total_score": 40
    },
    {
      "ticker": "INDIGO",
      "timestamp": "2025-07-31 10:45:23",
      "close": 5785.0,
      "volume": 1344,
      "vsr": 0.06014477707051975,
      "price_change_1h": 0.35,
      "price_change_3h": 1.16,
      "price_change_1d": 0.49,
      "rsi": 50.0,
      "bb_position": 0.5,
      "atr": 8.321428571428571,
      "sector": "Industrials",
      "volume_ratio": 0.22417186509657405,
      "momentum_score": 20,
      "momentum_status": "Neutral",
      "appearances": 1,
      "persistence_score": 10,
      "total_score": 30
    },
    {
      "ticker": "PGEL",
      "timestamp": "2025-07-31 10:45:23",
      "close": 795.5,
      "volume": 441,
      "vsr": 0.08923189247658404,
      "price_change_1h": -0.43,
      "price_change_3h": -1.38,
      "price_change_1d": -0.86,
      "rsi": 50.0,
      "bb_position": 0.5,
      "atr": 1.0000000000000162,
      "sector": "Unknown",
      "volume_ratio": 0.303155289750464,
      "momentum_score": 45,
      "momentum_status": "Weak Short",
      "appearances": 5,
      "persistence_score": 50,
      "total_score": 95
    },
    {
      "ticker": "APLLTD",
      "timestamp": "2025-07-31 10:45:24",
      "close": 993.1,
      "volume": 0,
      "vsr": 0.0,
      "price_change_1h": -0.51,
      "price_change_3h": -1.55,
      "price_change_1d": -0.93,
      "rsi": 50.0,
      "bb_position": 0.5,
      "atr": 0.9928571428571412,
      "sector": "Healthcare",
      "volume_ratio": 0.0,
      "momentum_score": 65,
      "momentum_status": "Short",
      "appearances": 12,
      "persistence_score": 120,
      "total_score": 185
    },
    {
      "ticker": "TATACONSUM",
      "timestamp": "2025-07-31 10:45:24",
      "close": 1072.5,
      "volume": 199,
      "vsr": 0.00976445101949312,
      "price_change_1h": 0.73,
      "price_change_3h": -0.49,
      "price_change_1d": -0.77,
      "rsi": 50.0,
      "bb_position": 0.5,
      "atr": 1.2285714285713993,
      "sector": "Unknown",
      "volume_ratio": 0.10021907184045527,
      "momentum_score": 20,
      "momentum_status": "Neutral",
      "appearances": 4,
      "persistence_score": 40,
      "total_score": 60
    },
    {
      "ticker": "BLS",
      "timestamp": "2025-07-31 10:45:24",
      "close": 372.8,
      "volume": 9943,
      "vsr": 9.618007525706535,
      "price_change_1h": -0.11,
      "price_change_3h": -1.13,
      "price_change_1d": -1.06,
      "rsi": 50.0,
      "bb_position": 0.5,
      "atr": 0.29642857142856166,
      "sector": "Industrials",
      "volume_ratio": 7.092264346089375,
      "momentum_score": 35,
      "momentum_status": "Neutral",
      "appearances": 3,
      "persistence_score": 30,
      "total_score": 65
    },
    {
      "ticker": "HDFCLIFE",
      "timestamp": "2025-07-31 10:45:24",
      "close": 752.1,
      "volume": 462,
      "vsr": 0.06501713824321138,
      "price_change_1h": -0.36,
      "price_change_3h": -0.67,
      "price_change_1d": -0.4,
      "rsi": 50.0,
      "bb_position": 0.5,
      "atr": 0.9428571428571461,
      "sector": "Financial Services",
      "volume_ratio": 0.12130919402906695,
      "momentum_score": 20,
      "momentum_status": "Neutral",
      "appearances": 1,
      "persistence_score": 10,
      "total_score": 30
    },
    {
      "ticker": "LXCHEM",
      "timestamp": "2025-07-31 10:45:24",
      "close": 203.7,
      "volume": 301,
      "vsr": 0.02141924434898478,
      "price_change_1h": 2.93,
      "price_change_3h": 1.71,
      "price_change_1d": -0.36,
      "rsi": 50.0,
      "bb_position": 0.5,
      "atr": 0.26357142857143046,
      "sector": "Unknown",
      "volume_ratio": 0.1129159320253592,
      "momentum_score": 20,
      "momentum_status": "Neutral",
      "appearances": 6,
      "persistence_score": 60,
      "total_score": 80
    },
    {
      "ticker": "POLYPLEX",
      "timestamp": "2025-07-31 10:45:24",
      "close": 1109.0,
      "volume": 0,
      "vsr": 0.0,
      "price_change_1h": -0.09,
      "price_change_3h": 0.32,
      "price_change_1d": -0.22,
      "rsi": 50.0,
      "bb_position": 0.5,
      "atr": 0.2928571428571526,
      "sector": "Basic Materials",
      "volume_ratio": 0.0,
      "momentum_score": 20,
      "momentum_status": "Neutral",
      "appearances": 13,
      "persistence_score": 130,
      "total_score": 150
    },
    {
      "ticker": "TECHM",
      "timestamp": "2025-07-31 10:45:24",
      "close": 1454.4,
      "volume": 1867,
      "vsr": 0.030424360346944037,
      "price_change_1h": 0.21,
      "price_change_3h": -0.23,
      "price_change_1d": -0.8,
      "rsi": 50.0,
      "bb_position": 0.5,
      "atr": 0.8642857142856916,
      "sector": "Unknown",
      "volume_ratio": 0.3768291452215158,
      "momentum_score": 20,
      "momentum_status": "Neutral",
      "appearances": 1,
      "persistence_score": 10,
      "total_score": 30
    },
    {
      "ticker": "INTELLECT",
      "timestamp": "2025-07-31 10:45:24",
      "close": 1028.1,
      "volume": 25,
      "vsr": 0.024191109767165164,
      "price_change_1h": -0.67,
      "price_change_3h": -2.49,
      "price_change_1d": -2.41,
      "rsi": 50.0,
      "bb_position": 0.5,
      "atr": 1.2500000000000486,
      "sector": "Technology",
      "volume_ratio": 0.08874689385871495,
      "momentum_score": 95,
      "momentum_status": "Strong Short",
      "appearances": 3,
      "persistence_score": 30,
      "total_score": 125
    },
    {
      "ticker": "ONGC",
      "timestamp": "2025-07-31 10:45:24",
      "close": 241.32,
      "volume": 26586,
      "vsr": 0.035434485877654,
      "price_change_1h": 0.03,
      "price_change_3h": -0.59,
      "price_change_1d": -0.26,
      "rsi": 50.0,
      "bb_position": 0.5,
      "atr": 0.16928571428571257,
      "sector": "Unknown",
      "volume_ratio": 0.49884230158700377,
      "momentum_score": 20,
      "momentum_status": "Neutral",
      "appearances": 4,
      "persistence_score": 40,
      "total_score": 60
    },
    {
      "ticker": "WESTLIFE",
      "timestamp": "2025-07-31 10:45:24",
      "close": 737.65,
      "volume": 0,
      "vsr": 0.0,
      "price_change_1h": -1.32,
      "price_change_3h": -2.01,
      "price_change_1d": -0.45,
      "rsi": 50.0,
      "bb_position": 0.5,
      "atr": 0.20714285714287176,
      "sector": "Unknown",
      "volume_ratio": 0.0,
      "momentum_score": 65,
      "momentum_status": "Short",
      "appearances": 13,
      "persistence_score": 130,
      "total_score": 195
    },
    {
      "ticker": "BBTC",
      "timestamp": "2025-07-31 10:45:24",
      "close": 1911.4,
      "volume": 0,
      "vsr": 0.0,
      "price_change_1h": -0.14,
      "price_change_3h": -1.68,
      "price_change_1d": -1.13,
      "rsi": 50.0,
      "bb_position": 0.5,
      "atr": 0.6714285714285779,
      "sector": "Consumer Defensive",
      "volume_ratio": 0.0,
      "momentum_score": 45,
      "momentum_status": "Weak Short",
      "appearances": 6,
      "persistence_score": 60,
      "total_score": 105
    },
    {
      "ticker": "ACE",
      "timestamp": "2025-07-31 10:45:24",
      "close": 1119.4,
      "volume": 15,
      "vsr": 0.0052592826338440386,
      "price_change_1h": -0.01,
      "price_change_3h": -1.34,
      "price_change_1d": -1.72,
      "rsi": 50.0,
      "bb_position": 0.5,
      "atr": 1.2928571428571363,
      "sector": "Industrials",
      "volume_ratio": 0.08688097306689835,
      "momentum_score": 45,
      "momentum_status": "Weak Short",
      "appearances": 1,
      "persistence_score": 10,
      "total_score": 55
    },
    {
      "ticker": "ITC",
      "timestamp": "2025-07-31 10:45:24",
      "close": 411.7,
      "volume": 2336,
      "vsr": 0.019270648043602737,
      "price_change_1h": 0.93,
      "price_change_3h": 0.8,
      "price_change_1d": 0.05,
      "rsi": 50.0,
      "bb_position": 0.5,
      "atr": 0.40714285714285225,
      "sector": "Consumer Defensive",
      "volume_ratio": 0.10255127014752721,
      "momentum_score": 20,
      "momentum_status": "Neutral",
      "appearances": 7,
      "persistence_score": 70,
      "total_score": 90
    },
    {
      "ticker": "AVANTIFEED",
      "timestamp": "2025-07-31 10:45:25",
      "close": 667.75,
      "volume": 897,
      "vsr": 0.30335952923461634,
      "price_change_1h": 0.75,
      "price_change_3h": -3.11,
      "price_change_1d": -4.14,
      "rsi": 50.0,
      "bb_position": 0.5,
      "atr": 0.3071428571428377,
      "sector": "Consumer Defensive",
      "volume_ratio": 1.11304132026306,
      "momentum_score": 75,
      "momentum_status": "Short",
      "appearances": 1,
      "persistence_score": 10,
      "total_score": 85
    },
    {
      "ticker": "MAZDOCK",
      "timestamp": "2025-07-31 10:45:25",
      "close": 2753.0,
      "volume": 1347,
      "vsr": 0.07838969981458924,
      "price_change_1h": -0.97,
      "price_change_3h": 1.08,
      "price_change_1d": 0.73,
      "rsi": 50.0,
      "bb_position": 0.5,
      "atr": 4.600000000000007,
      "sector": "Unknown",
      "volume_ratio": 0.37439546389460227,
      "momentum_score": 40,
      "momentum_status": "Weak Short",
      "appearances": 4,
      "persistence_score": 40,
      "total_score": 80
    },
    {
      "ticker": "JWL",
      "timestamp": "2025-07-31 10:45:25",
      "close": 342.5,
      "volume": 126,
      "vsr": 0.024757095560429664,
      "price_change_1h": -0.58,
      "price_change_3h": -1.47,
      "price_change_1d": -1.13,
      "rsi": 50.0,
      "bb_position": 0.5,
      "atr": 0.2464285714285747,
      "sector": "Industrials",
      "volume_ratio": 0.1680672268907563,
      "momentum_score": 65,
      "momentum_status": "Short",
      "appearances": 9,
      "persistence_score": 90,
      "total_score": 155
    },
    {
      "ticker": "AXISBANK",
      "timestamp": "2025-07-31 10:45:25",
      "close": 1066.3,
      "volume": 5615,
      "vsr": 0.27779371923985235,
      "price_change_1h": -0.36,
      "price_change_3h": -0.66,
      "price_change_1d": -0.29,
      "rsi": 50.0,
      "bb_position": 0.5,
      "atr": 0.75,
      "sector": "Financial Services",
      "volume_ratio": 0.49334229520583756,
      "momentum_score": 20,
      "momentum_status": "Neutral",
      "appearances": 1,
      "persistence_score": 10,
      "total_score": 30
    },
    {
      "ticker": "BRIGADE",
      "timestamp": "2025-07-31 10:45:25",
      "close": 976.1,
      "volume": 3,
      "vsr": 0.0,
      "price_change_1h": -0.4,
      "price_change_3h": -1.48,
      "price_change_1d": -0.63,
      "rsi": 50.0,
      "bb_position": 0.5,
      "atr": 0.8571428571428653,
      "sector": "Real Estate",
      "volume_ratio": 0.01741654571843251,
      "momentum_score": 45,
      "momentum_status": "Weak Short",
      "appearances": 1,
      "persistence_score": 10,
      "total_score": 55
    },
    {
      "ticker": "IRFC",
      "timestamp": "2025-07-31 10:45:25",
      "close": 128.82,
      "volume": 13376,
      "vsr": 0.7145005253523736,
      "price_change_1h": -0.72,
      "price_change_3h": -2.08,
      "price_change_1d": -1.25,
      "rsi": 50.0,
      "bb_position": 0.5,
      "atr": 0.1135714285714349,
      "sector": "Financial Services",
      "volume_ratio": 0.6171748654428677,
      "momentum_score": 55,
      "momentum_status": "Weak Short",
      "appearances": 1,
      "persistence_score": 10,
      "total_score": 65
    },
    {
      "ticker": "GRANULES",
      "timestamp": "2025-07-31 10:45:25",
      "close": 480.0,
      "volume": 1828,
      "vsr": 2.6478194002444537,
      "price_change_1h": -0.97,
      "price_change_3h": -2.43,
      "price_change_1d": -1.57,
      "rsi": 50.0,
      "bb_position": 0.5,
      "atr": 0.49999999999999595,
      "sector": "Healthcare",
      "volume_ratio": 2.238413028837323,
      "momentum_score": 55,
      "momentum_status": "Weak Short",
      "appearances": 1,
      "persistence_score": 10,
      "total_score": 65
    },
    {
      "ticker": "ELECON",
      "timestamp": "2025-07-31 10:45:25",
      "close": 570.75,
      "volume": 0,
      "vsr": 0.0,
      "price_change_1h": 0.17,
      "price_change_3h": -1.65,
      "price_change_1d": -1.45,
      "rsi": 50.0,
      "bb_position": 0.5,
      "atr": 0.33571428571428896,
      "sector": "Industrials",
      "volume_ratio": 0.0,
      "momentum_score": 45,
      "momentum_status": "Weak Short",
      "appearances": 11,
      "persistence_score": 110,
      "total_score": 155
    },
    {
      "ticker": "PNCINFRA",
      "timestamp": "2025-07-31 10:45:25",
      "close": 315.7,
      "volume": 56,
      "vsr": 0.0,
      "price_change_1h": 0.37,
      "price_change_3h": 0.41,
      "price_change_1d": -0.14,
      "rsi": 50.0,
      "bb_position": 0.5,
      "atr": 0.21785714285713148,
      "sector": "Unknown",
      "volume_ratio": 0.11379800853485063,
      "momentum_score": 20,
      "momentum_status": "Neutral",
      "appearances": 3,
      "persistence_score": 30,
      "total_score": 50
    },
    {
      "ticker": "GAEL",
      "timestamp": "2025-07-31 10:45:25",
      "close": 107.88,
      "volume": 23,
      "vsr": 0.0,
      "price_change_1h": -0.53,
      "price_change_3h": -1.81,
      "price_change_1d": -1.18,
      "rsi": 50.0,
      "bb_position": 0.5,
      "atr": 0.05071428571428527,
      "sector": "Consumer Defensive",
      "volume_ratio": 0.14533965244865718,
      "momentum_score": 65,
      "momentum_status": "Short",
      "appearances": 8,
      "persistence_score": 80,
      "total_score": 145
    },
    {
      "ticker": "SAPPHIRE",
      "timestamp": "2025-07-31 10:45:25",
      "close": 320.65,
      "volume": 0,
      "vsr": 0.0,
      "price_change_1h": -0.23,
      "price_change_3h": -1.11,
      "price_change_1d": 0.08,
      "rsi": 50.0,
      "bb_position": 0.5,
      "atr": 0.22499999999999837,
      "sector": "Unknown",
      "volume_ratio": 0.0,
      "momentum_score": 45,
      "momentum_status": "Weak Short",
      "appearances": 14,
      "persistence_score": 140,
      "total_score": 185
    },
    {
      "ticker": "JSWSTEEL",
      "timestamp": "2025-07-31 10:45:26",
      "close": 1042.9,
      "volume": 1208,
      "vsr": 0.0,
      "price_change_1h": 0.13,
      "price_change_3h": 0.67,
      "price_change_1d": 0.31,
      "rsi": 50.0,
      "bb_position": 0.5,
      "atr": 1.0357142857142532,
      "sector": "Basic Materials",
      "volume_ratio": 0.21240494087652204,
      "momentum_score": 20,
      "momentum_status": "Neutral",
      "appearances": 14,
      "persistence_score": 140,
      "total_score": 160
    },
    {
      "ticker": "FORCEMOT",
      "timestamp": "2025-07-31 10:45:26",
      "close": 17297.0,
      "volume": 3,
      "vsr": 0.008186097278122655,
      "price_change_1h": -0.84,
      "price_change_3h": -2.4,
      "price_change_1d": -0.74,
      "rsi": 50.0,
      "bb_position": 0.5,
      "atr": 25.785714285714285,
      "sector": "Unknown",
      "volume_ratio": 0.016012810248198558,
      "momentum_score": 65,
      "momentum_status": "Short",
      "appearances": 2,
      "persistence_score": 20,
      "total_score": 85
    },
    {
      "ticker": "TATAMOTORS",
      "timestamp": "2025-07-31 10:45:26",
      "close": 665.95,
      "volume": 572,
      "vsr": 0.0033796533935023304,
      "price_change_1h": -0.15,
      "price_change_3h": -0.44,
      "price_change_1d": -0.22,
      "rsi": 50.0,
      "bb_position": 0.5,
      "atr": 0.38928571428572567,
      "sector": "Unknown",
      "volume_ratio": 0.018745493871665464,
      "momentum_score": 20,
      "momentum_status": "Neutral",
      "appearances": 11,
      "persistence_score": 110,
      "total_score": 130
    },
    {
      "ticker": "ICICIGI",
      "timestamp": "2025-07-31 10:45:26",
      "close": 1903.5,
      "volume": 144,
      "vsr": 0.0,
      "price_change_1h": -0.1,
      "price_change_3h": -0.6,
      "price_change_1d": -0.84,
      "rsi": 50.0,
      "bb_position": 0.5,
      "atr": 0.6357142857142922,
      "sector": "Financial Services",
      "volume_ratio": 0.24006001500375093,
      "momentum_score": 20,
      "momentum_status": "Neutral",
      "appearances": 6,
      "persistence_score": 60,
      "total_score": 80
    },
    {
      "ticker": "3MINDIA",
      "timestamp": "2025-07-31 10:45:26",
      "close": 30390.0,
      "volume": 4,
      "vsr": 0.05952380952380952,
      "price_change_1h": -1.25,
      "price_change_3h": -2.31,
      "price_change_1d": -0.58,
      "rsi": 50.0,
      "bb_position": 0.5,
      "atr": 28.928571428571427,
      "sector": "Industrials",
      "volume_ratio": 0.5755395683453237,
      "momentum_score": 65,
      "momentum_status": "Short",
      "appearances": 2,
      "persistence_score": 20,
      "total_score": 85
    },
    {
      "ticker": "SMSPHARMA",
      "timestamp": "2025-07-31 10:45:26",
      "close": 232.95,
      "volume": 0,
      "vsr": 0.0,
      "price_change_1h": -0.68,
      "price_change_3h": -1.85,
      "price_change_1d": -0.91,
      "rsi": 50.0,
      "bb_position": 0.5,
      "atr": 0.03571428571428571,
      "sector": "Healthcare",
      "volume_ratio": 0.0,
      "momentum_score": 65,
      "momentum_status": "Short",
      "appearances": 14,
      "persistence_score": 140,
      "total_score": 205
    },
    {
      "ticker": "SUNTV",
      "timestamp": "2025-07-31 10:45:26",
      "close": 561.1,
      "volume": 8,
      "vsr": 0.07361822050956407,
      "price_change_1h": -0.65,
      "price_change_3h": -1.79,
      "price_change_1d": -0.55,
      "rsi": 50.0,
      "bb_position": 0.5,
      "atr": 0.19642857142858766,
      "sector": "Unknown",
      "volume_ratio": 0.0544959128065395,
      "momentum_score": 65,
      "momentum_status": "Short",
      "appearances": 14,
      "persistence_score": 140,
      "total_score": 205
    },
    {
      "ticker": "GMRAIRPORT",
      "timestamp": "2025-07-31 10:45:26",
      "close": 90.01,
      "volume": 16810,
      "vsr": 0.0,
      "price_change_1h": -0.4,
      "price_change_3h": -0.01,
      "price_change_1d": 0.59,
      "rsi": 50.0,
      "bb_position": 0.5,
      "atr": 0.0835714285714287,
      "sector": "Unknown",
      "volume_ratio": 0.9645591918589138,
      "momentum_score": 20,
      "momentum_status": "Neutral",
      "appearances": 13,
      "persistence_score": 130,
      "total_score": 150
    },
    {
      "ticker": "IFCI",
      "timestamp": "2025-07-31 10:45:26",
      "close": 57.55,
      "volume": 2805,
      "vsr": 0.41513350316065356,
      "price_change_1h": -0.59,
      "price_change_3h": -2.37,
      "price_change_1d": -0.97,
      "rsi": 50.0,
      "bb_position": 0.5,
      "atr": 0.04285714285714499,
      "sector": "Financial Services",
      "volume_ratio": 0.5802227807254335,
      "momentum_score": 65,
      "momentum_status": "Short",
      "appearances": 7,
      "persistence_score": 70,
      "total_score": 135
    },
    {
      "ticker": "DIVISLAB",
      "timestamp": "2025-07-31 10:45:26",
      "close": 6598.5,
      "volume": 0,
      "vsr": 0.0,
      "price_change_1h": -0.55,
      "price_change_3h": -0.66,
      "price_change_1d": -0.23,
      "rsi": 50.0,
      "bb_position": 0.5,
      "atr": 5.642857142857143,
      "sector": "Healthcare",
      "volume_ratio": 0.0,
      "momentum_score": 40,
      "momentum_status": "Weak Short",
      "appearances": 1,
      "persistence_score": 10,
      "total_score": 50
    },
    {
      "ticker": "RADIANTCMS",
      "timestamp": "2025-07-31 10:45:26",
      "close": 55.51,
      "volume": 0,
      "vsr": 0.0,
      "price_change_1h": 0.02,
      "price_change_3h": 0.04,
      "price_change_1d": 0.09,
      "rsi": 50.0,
      "bb_position": 0.5,
      "atr": 0.035714285714285206,
      "sector": "Industrials",
      "volume_ratio": 0.0,
      "momentum_score": 20,
      "momentum_status": "Neutral",
      "appearances": 1,
      "persistence_score": 10,
      "total_score": 30
    },
    {
      "ticker": "DOMS",
      "timestamp": "2025-07-31 10:45:26",
      "close": 2340.0,
      "volume": 0,
      "vsr": 0.0,
      "price_change_1h": -0.97,
      "price_change_3h": -0.02,
      "price_change_1d": 1.18,
      "rsi": 50.0,
      "bb_position": 0.5,
      "atr": 1.3928571428571104,
      "sector": "Industrials",
      "volume_ratio": 0.0,
      "momentum_score": 40,
      "momentum_status": "Weak Short",
      "appearances": 4,
      "persistence_score": 40,
      "total_score": 80
    },
    {
      "ticker": "INDIAMART",
      "timestamp": "2025-07-31 10:45:27",
      "close": 2592.7,
      "volume": 0,
      "vsr": 0.0,
      "price_change_1h": -0.67,
      "price_change_3h": 0.11,
      "price_change_1d": 0.97,
      "rsi": 50.0,
      "bb_position": 0.5,
      "atr": 2.142857142857143,
      "sector": "Communication Services",
      "volume_ratio": 0.0,
      "momentum_score": 40,
      "momentum_status": "Weak Short",
      "appearances": 1,
      "persistence_score": 10,
      "total_score": 50
    },
    {
      "ticker": "UBL",
      "timestamp": "2025-07-31 10:45:27",
      "close": 1953.9,
      "volume": 0,
      "vsr": 0.0,
      "price_change_1h": 0.26,
      "price_change_3h": 0.2,
      "price_change_1d": -0.13,
      "rsi": 50.0,
      "bb_position": 0.5,
      "atr": 1.1500000000000097,
      "sector": "Unknown",
      "volume_ratio": 0.0,
      "momentum_score": 20,
      "momentum_status": "Neutral",
      "appearances": 10,
      "persistence_score": 100,
      "total_score": 120
    },
    {
      "ticker": "TITAN",
      "timestamp": "2025-07-31 10:45:27",
      "close": 3338.6,
      "volume": 0,
      "vsr": 0.0,
      "price_change_1h": -0.27,
      "price_change_3h": -0.34,
      "price_change_1d": -0.85,
      "rsi": 50.0,
      "bb_position": 0.5,
      "atr": 2.2714285714285842,
      "sector": "Unknown",
      "volume_ratio": 0.0,
      "momentum_score": 20,
      "momentum_status": "Neutral",
      "appearances": 17,
      "persistence_score": 170,
      "total_score": 190
    },
    {
      "ticker": "TMB",
      "timestamp": "2025-07-31 10:45:27",
      "close": 458.25,
      "volume": 1230,
      "vsr": 0.0,
      "price_change_1h": -0.07,
      "price_change_3h": 0.67,
      "price_change_1d": -0.33,
      "rsi": 50.0,
      "bb_position": 0.5,
      "atr": 0.25714285714285473,
      "sector": "Unknown",
      "volume_ratio": 4.617117117117117,
      "momentum_score": 30,
      "momentum_status": "Neutral",
      "appearances": 1,
      "persistence_score": 10,
      "total_score": 40
    },
    {
      "ticker": "SAFARI",
      "timestamp": "2025-07-31 10:45:27",
      "close": 2042.8,
      "volume": 0,
      "vsr": 0.0,
      "price_change_1h": 0.12,
      "price_change_3h": 0.68,
      "price_change_1d": 0.24,
      "rsi": 50.0,
      "bb_position": 0.5,
      "atr": 2.850000000000039,
      "sector": "Unknown",
      "volume_ratio": 0.0,
      "momentum_score": 20,
      "momentum_status": "Neutral",
      "appearances": 1,
      "persistence_score": 10,
      "total_score": 30
    },
    {
      "ticker": "COALINDIA",
      "timestamp": "2025-07-31 10:45:27",
      "close": 376.45,
      "volume": 8637,
      "vsr": 0.08478701234827558,
      "price_change_1h": 0.15,
      "price_change_3h": -1.23,
      "price_change_1d": -1.0,
      "rsi": 50.0,
      "bb_position": 0.5,
      "atr": 0.27142857142857224,
      "sector": "Energy",
      "volume_ratio": 0.3937336314713384,
      "momentum_score": 45,
      "momentum_status": "Weak Short",
      "appearances": 13,
      "persistence_score": 130,
      "total_score": 175
    },
    {
      "ticker": "IEX",
      "timestamp": "2025-07-31 10:45:27",
      "close": 136.95,
      "volume": 315,
      "vsr": 0.0014310567295415014,
      "price_change_1h": -1.86,
      "price_change_3h": -0.1,
      "price_change_1d": 2.54,
      "rsi": 50.0,
      "bb_position": 0.5,
      "atr": 0.19428571428571217,
      "sector": "Financial Services",
      "volume_ratio": 0.006774710757487938,
      "momentum_score": 40,
      "momentum_status": "Weak Short",
      "appearances": 4,
      "persistence_score": 40,
      "total_score": 80
    },
    {
      "ticker": "MINDACORP",
      "timestamp": "2025-07-31 10:45:27",
      "close": 500.15,
      "volume": 25643,
      "vsr": 14.00631776347459,
      "price_change_1h": -0.75,
      "price_change_3h": -0.96,
      "price_change_1d": -0.39,
      "rsi": 50.0,
      "bb_position": 0.5,
      "atr": 0.3678571428571494,
      "sector": "Unknown",
      "volume_ratio": 17.20602543026806,
      "momentum_score": 30,
      "momentum_status": "Neutral",
      "appearances": 6,
      "persistence_score": 60,
      "total_score": 90
    },
    {
      "ticker": "SPARC",
      "timestamp": "2025-07-31 10:45:27",
      "close": 150.1,
      "volume": 11,
      "vsr": 0.0,
      "price_change_1h": -0.4,
      "price_change_3h": -0.81,
      "price_change_1d": -0.8,
      "rsi": 50.0,
      "bb_position": 0.5,
      "atr": 0.08071428571428539,
      "sector": "Unknown",
      "volume_ratio": 0.03007518796992481,
      "momentum_score": 20,
      "momentum_status": "Neutral",
      "appearances": 13,
      "persistence_score": 130,
      "total_score": 150
    },
    {
      "ticker": "ADANIENSOL",
      "timestamp": "2025-07-31 10:45:27",
      "close": 811.0,
      "volume": 187,
      "vsr": 0.03789145213418829,
      "price_change_1h": -0.43,
      "price_change_3h": -2.07,
      "price_change_1d": -1.14,
      "rsi": 50.0,
      "bb_position": 0.5,
      "atr": 0.7857142857142776,
      "sector": "Utilities",
      "volume_ratio": 0.17511002902893527,
      "momentum_score": 45,
      "momentum_status": "Weak Short",
      "appearances": 5,
      "persistence_score": 50,
      "total_score": 95
    },
    {
      "ticker": "POLICYBZR",
      "timestamp": "2025-07-31 10:45:27",
      "close": 1794.2,
      "volume": 272,
      "vsr": 0.32698124185551836,
      "price_change_1h": -0.26,
      "price_change_3h": -1.95,
      "price_change_1d": -1.24,
      "rsi": 50.0,
      "bb_position": 0.5,
      "atr": 2.192857142857162,
      "sector": "Unknown",
      "volume_ratio": 0.3407880724174654,
      "momentum_score": 45,
      "momentum_status": "Weak Short",
      "appearances": 5,
      "persistence_score": 50,
      "total_score": 95
    },
    {
      "ticker": "APOLLOTYRE",
      "timestamp": "2025-07-31 10:45:28",
      "close": 453.3,
      "volume": 175,
      "vsr": 0.2266105535772,
      "price_change_1h": -0.58,
      "price_change_3h": -1.42,
      "price_change_1d": -0.89,
      "rsi": 50.0,
      "bb_position": 0.5,
      "atr": 0.21785714285713148,
      "sector": "Consumer Cyclical",
      "volume_ratio": 0.5229344090841178,
      "momentum_score": 65,
      "momentum_status": "Short",
      "appearances": 2,
      "persistence_score": 20,
      "total_score": 85
    },
    {
      "ticker": "BATAINDIA",
      "timestamp": "2025-07-31 10:45:28",
      "close": 1192.5,
      "volume": 0,
      "vsr": 0.0,
      "price_change_1h": -0.02,
      "price_change_3h": -0.54,
      "price_change_1d": -0.62,
      "rsi": 50.0,
      "bb_position": 0.5,
      "atr": 0.5428571428571526,
      "sector": "Consumer Cyclical",
      "volume_ratio": 0.0,
      "momentum_score": 20,
      "momentum_status": "Neutral",
      "appearances": 4,
      "persistence_score": 40,
      "total_score": 60
    },
    {
      "ticker": "INOXWIND",
      "timestamp": "2025-07-31 10:45:28",
      "close": 152.29,
      "volume": 3239,
      "vsr": 0.03857780999763683,
      "price_change_1h": -0.59,
      "price_change_3h": -2.35,
      "price_change_1d": -1.9,
      "rsi": 50.0,
      "bb_position": 0.5,
      "atr": 0.13857142857143043,
      "sector": "Industrials",
      "volume_ratio": 0.3970846946468962,
      "momentum_score": 65,
      "momentum_status": "Short",
      "appearances": 1,
      "persistence_score": 10,
      "total_score": 75
    },
    {
      "ticker": "KEI",
      "timestamp": "2025-07-31 10:45:28",
      "close": 3824.6,
      "volume": 9,
      "vsr": 0.0037663060615140903,
      "price_change_1h": -0.71,
      "price_change_3h": -1.71,
      "price_change_1d": -1.27,
      "rsi": 50.0,
      "bb_position": 0.5,
      "atr": 4.3785714285714095,
      "sector": "Industrials",
      "volume_ratio": 0.0036410712840844726,
      "momentum_score": 65,
      "momentum_status": "Short",
      "appearances": 1,
      "persistence_score": 10,
      "total_score": 75
    }
  ]
}